{
  "_meta": {
    "fixtureName": "y_and_height_override",
    "description": "rowOverrides에 y와 height 모두 지정한 케이스. saved rows[1] = {y:555, height:90}, rows[2].y = 555 + 90 = 645."
  },
  "templateName": "행Y높이_모두",
  "documentType": "invoice_statement",
  "loaded": {
    "src": "data:image/png;base64,iVBORw0KGgo=",
    "fileName": "y_h.png",
    "naturalWidth": 1200,
    "naturalHeight": 1600
  },
  "regions": [
    {
      "id": "table_1",
      "name": "items",
      "fieldType": "table",
      "x": 60,
      "y": 480,
      "width": 1080,
      "height": 600,
      "table": {
        "mode": "repeat",
        "rowTemplate": { "x": 60, "y": 480, "width": 1080, "height": 60 },
        "rows": [
          { "x": 60, "y": 480, "width": 1080, "height": 60 },
          { "x": 60, "y": 540, "width": 1080, "height": 60 },
          { "x": 60, "y": 600, "width": 1080, "height": 60 }
        ],
        "rowOverrides": [
          { "rowIndex": 1, "y": 555, "height": 90, "locked": true }
        ]
      }
    }
  ]
}
