{
  "rows": [
    {
      "rowIndex": 1,
      "itemCode": "DPNL30M",
      "itemName": "두피나액30ML",
      "spec": "",
      "lotNo": "",
      "serialNo": "",
      "manufacturingNo": "",
      "expiryDate": "",
      "quantity": "10Q",
      "unit": "",
      "unitPrice": "2,730",
      "supplyAmount": "",
      "taxAmount": "",
      "amount": "273,000",
      "totalAmount": "",
      "manufacturer": "",
      "insuranceCode": "",
      "remark": "",
      "_rawText": "두피나액30ML DPNL30M 10Q 2,730 273,000",
      "_confidence": null,
      "_source": "invoice_statement_table_parser"
    },
    {
      "rowIndex": 2,
      "itemCode": "INAP250G",
      "itemName": "노루모에이스산250G캔 10 <",
      "spec": "",
      "lotNo": "",
      "serialNo": "",
      "manufacturingNo": "",
      "expiryDate": "",
      "quantity": "100",
      "unit": "",
      "unitPrice": "4,000",
      "supplyAmount": "",
      "taxAmount": "",
      "amount": "400,000",
      "totalAmount": "",
      "manufacturer": "",
      "insuranceCode": "",
      "remark": "",
      "_rawText": "노루모에이스산250G캔 10 < INAP250G 100 4,000 400,000",
      "_confidence": null,
      "_source": "invoice_statement_table_parser"
    },
    {
      "rowIndex": 3,
      "itemCode": "NASP15P",
      "itemName": "노루모에스산15P",
      "spec": "",
      "lotNo": "",
      "serialNo": "",
      "manufacturingNo": "",
      "expiryDate": "",
      "quantity": "200",
      "unit": "",
      "unitPrice": "2,300",
      "supplyAmount": "",
      "taxAmount": "",
      "amount": "460,000",
      "totalAmount": "",
      "manufacturer": "",
      "insuranceCode": "",
      "remark": "",
      "_rawText": "노루모에스산15P NASP15P 200 2,300 460,000",
      "_confidence": null,
      "_source": "invoice_statement_table_parser"
    },
    {
      "rowIndex": 4,
      "itemCode": "NPRT10T",
      "itemName": "나프록센나트륨정10T 100",
      "spec": "",
      "lotNo": "",
      "serialNo": "",
      "manufacturingNo": "",
      "expiryDate": "",
      "quantity": "300",
      "unit": "",
      "unitPrice": "545",
      "supplyAmount": "",
      "taxAmount": "",
      "amount": "163,635",
      "totalAmount": "",
      "manufacturer": "",
      "insuranceCode": "",
      "remark": "",
      "_rawText": "나프록센나트륨정10T 100 NPRT10T 300 545 163,635",
      "_confidence": null,
      "_source": "invoice_statement_table_parser"
    },
    {
      "rowIndex": 5,
      "itemCode": "NRDA4P",
      "itemName": "노루모듀얼액션현탁액4P",
      "spec": "",
      "lotNo": "",
      "serialNo": "",
      "manufacturingNo": "",
      "expiryDate": "",
      "quantity": "",
      "unit": "",
      "unitPrice": "2,000",
      "supplyAmount": "",
      "taxAmount": "",
      "amount": "100,000",
      "totalAmount": "",
      "manufacturer": "",
      "insuranceCode": "",
      "remark": "",
      "_rawText": "노루모듀얼액션현탁액4P NRDA4P 2,000 100,000",
      "_confidence": null,
      "_source": "invoice_statement_table_parser"
    },
    {
      "rowIndex": 6,
      "itemCode": "NRFS75M",
      "itemName": "노루모에프내복액75ML",
      "spec": "",
      "lotNo": "",
      "serialNo": "",
      "manufacturingNo": "",
      "expiryDate": "",
      "quantity": "3,000",
      "unit": "",
      "unitPrice": "550",
      "supplyAmount": "",
      "taxAmount": "",
      "amount": "1,650,000",
      "totalAmount": "",
      "manufacturer": "",
      "insuranceCode": "",
      "remark": "",
      "_rawText": "노루모에프내복액75ML NRFS75M 3,000 550 1,650,000",
      "_confidence": null,
      "_source": "invoice_statement_table_parser"
    }
  ],
  "displayCols": [
    {
      "key": "itemName",
      "labelKo": "품목"
    },
    {
      "key": "itemCode",
      "labelKo": "품목코드"
    },
    {
      "key": "quantity",
      "labelKo": "수량"
    },
    {
      "key": "unitPrice",
      "labelKo": "단가"
    },
    {
      "key": "amount",
      "labelKo": "금액"
    }
  ],
  "emptyValue": "-"
}
